README.md
setup.py
apim_api.egg-info/PKG-INFO
apim_api.egg-info/SOURCES.txt
apim_api.egg-info/dependency_links.txt
apim_api.egg-info/requires.txt
apim_api.egg-info/top_level.txt
apim_swagger_client/__init__.py
apim_swagger_client/api_client.py
apim_swagger_client/configuration.py
apim_swagger_client/rest.py
apim_swagger_client/api/__init__.py
apim_swagger_client/api/api_discovery_api.py
apim_swagger_client/api/api_manager_services_api.py
apim_swagger_client/api/api_proxy_registration_api.py
apim_swagger_client/api/api_repository_api.py
apim_swagger_client/api/applications_api.py
apim_swagger_client/api/current_user_api.py
apim_swagger_client/api/login_api.py
apim_swagger_client/api/metrics_api.py
apim_swagger_client/api/migrate_api.py
apim_swagger_client/api/o_auth_authorizations_api.py
apim_swagger_client/api/organizations_api.py
apim_swagger_client/api/quotas_api.py
apim_swagger_client/api/users_api.py
apim_swagger_client/models/__init__.py
apim_swagger_client/models/alert_config.py
apim_swagger_client/models/api.py
apim_swagger_client/models/api_access.py
apim_swagger_client/models/api_definition.py
apim_swagger_client/models/api_key.py
apim_swagger_client/models/api_promotion.py
apim_swagger_client/models/application.py
apim_swagger_client/models/application_request.py
apim_swagger_client/models/authenticated_user_attributes.py
apim_swagger_client/models/authentication_profile.py
apim_swagger_client/models/authorization.py
apim_swagger_client/models/authorization_code.py
apim_swagger_client/models/backend_blob.py
apim_swagger_client/models/backend_export.py
apim_swagger_client/models/backend_method_export.py
apim_swagger_client/models/ca_cert.py
apim_swagger_client/models/config.py
apim_swagger_client/models/cors_profile.py
apim_swagger_client/models/custom_properties_config.py
apim_swagger_client/models/custom_property.py
apim_swagger_client/models/custom_property_option.py
apim_swagger_client/models/custom_property_permission.py
apim_swagger_client/models/discovery_api.py
apim_swagger_client/models/error_response.py
apim_swagger_client/models/export_options.py
apim_swagger_client/models/external_client.py
