Metadata-Version: 1.0
Name: apim-api
Version: 1.1.0
Summary: API Manager API v1.3
Home-page: UNKNOWN
Author: UNKNOWN
Author-email: support@axway.com
License: UNKNOWN
Keywords: Swagger,API Manager API v1.3
Platform: UNKNOWN
